setup.py
salure_helpers/zermelo/__init__.py
salure_helpers/zermelo/zermelo.py
salure_helpers_zermelo.egg-info/PKG-INFO
salure_helpers_zermelo.egg-info/SOURCES.txt
salure_helpers_zermelo.egg-info/dependency_links.txt
salure_helpers_zermelo.egg-info/not-zip-safe
salure_helpers_zermelo.egg-info/requires.txt
salure_helpers_zermelo.egg-info/top_level.txt